bookstw/__init__.py
bookstw/ocr/__init__.py
bookstw/ocr/baidu.py
bookstw-0.1.1.dist-info/LICENSE
bookstw-0.1.1.dist-info/METADATA
bookstw-0.1.1.dist-info/WHEEL
bookstw-0.1.1.dist-info/RECORD
